mstt/__init__.py
mstt/cli.py
mstt/models.py
mstt/plugin.py
mstt/types.py
mstt-0.2.1.dist-info/WHEEL
mstt-0.2.1.dist-info/entry_points.txt
mstt-0.2.1.dist-info/METADATA
mstt-0.2.1.dist-info/RECORD
