Metadata-Version: 2.3
Name: mstt
Version: 0.2.1
Summary: mstt-A command-line tool and Python library for running speech-to-text against multiple models.
Author: Yunfeng Wang
Author-email: Yunfeng Wang <wyf.brz@gmail.com>
License: Apache-2.0
Requires-Dist: black>=24.8.0
Requires-Dist: click
Requires-Dist: pluggy
Requires-Dist: pydantic
Requires-Dist: pytest>=8.3.5
Requires-Dist: transformers[audio] ; extra == 'transformers'
Requires-Dist: torch ; extra == 'transformers'
Requires-Python: >=3.10
Provides-Extra: transformers
